{"id":"liter-to-pint","slug":"liter-to-pint","name":"Liters to Pints Converter","category":"converters","icon":"🍺","description":"Convert liters to US pints and UK pints. 1 liter = 2.11338 US pints.","tags":["liter","pint","volume","converter"],"fields":[{"id":"liters","label":"Liters (L)","type":"number","defaultValue":1},{"id":"usPints","label":"US Pints (pt)","type":"computed","precision":4},{"id":"ukPints","label":"UK Pints","type":"computed","precision":4},{"id":"cups","label":"US Cups","type":"computed","precision":4}],"groups":[{"id":"inputs","label":"Liters","fields":["liters"]},{"id":"outputs","label":"Converted","fields":["usPints","ukPints","cups"]}],"formulas":{"usPints":"liters * 2.11338","ukPints":"liters * 1.75975","cups":"liters * 4.22675"},"examples":[{"label":"1 liter","inputs":{"liters":1}},{"label":"2 liters","inputs":{"liters":2}}]}
